davidkhala/databricks/__init__.py
davidkhala/databricks/connect/__init__.py
davidkhala/databricks/connect/context.py
davidkhala/databricks/connect/notebook.py
davidkhala/databricks/gcp/__init__.py
davidkhala/databricks/gcp/pubsub.py
davidkhala/databricks/lineage/__init__.py
davidkhala/databricks/lineage/Column.sql
davidkhala/databricks/lineage/rest.py
davidkhala/databricks/lineage/sql.py
davidkhala/databricks/lineage/Table.sql
davidkhala/databricks/local.py
davidkhala/databricks/sink/__init__.py
davidkhala/databricks/sink/stream/__init__.py
davidkhala/databricks/workspace/__init__.py
davidkhala/databricks/workspace/app.py
davidkhala/databricks/workspace/catalog.py
davidkhala/databricks/workspace/job.py
davidkhala/databricks/workspace/path.py
davidkhala/databricks/workspace/server.py
davidkhala/databricks/workspace/table.py
davidkhala/databricks/workspace/types.py
davidkhala/databricks/workspace/volume.py
davidkhala/databricks/workspace/warehouse.py
davidkhala_databricks-0.1.3.dist-info/entry_points.txt
davidkhala_databricks-0.1.3.dist-info/METADATA
davidkhala_databricks-0.1.3.dist-info/WHEEL
davidkhala_databricks-0.1.3.dist-info/RECORD
